

L = []
print L[0:10]

def f():
    print 1
   # commentaire foireux
x = 1
s = "asd"

class A:
    def f():
        pass



===============================================================================
co_filename = '<?>'
co_varnames = ()
co_flags    = 64
  3           0 BUILD_LIST               0
              3 STORE_NAME               0 (L)

  4           6 LOAD_NAME                0 (L)
              9 LOAD_CONST               1 (0)
             12 LOAD_CONST               2 (10)
             15 SLICE+3             
             16 PRINT_ITEM          
             17 PRINT_NEWLINE       

  6          18 LOAD_CONST               3 (<pypy.interpreter.pycode.PyCode object at xxx>)
             21 MAKE_FUNCTION            0
             24 STORE_NAME               1 (f)

  9          27 LOAD_CONST               4 (1)
             30 STORE_NAME               2 (x)

 10          33 LOAD_CONST               5 ('asd')
             36 STORE_NAME               3 (s)

 12          39 LOAD_CONST               6 ('A')
             42 BUILD_TUPLE              0
             45 LOAD_CONST               7 (<pypy.interpreter.pycode.PyCode object at xxx>)
             48 MAKE_FUNCTION            0
             51 CALL_FUNCTION            0
             54 BUILD_CLASS         
             55 STORE_NAME               4 (A)
             58 LOAD_CONST               0 (None)
             61 RETURN_VALUE        
co_consts:
[0] None
[1] 0
[2] 10
[3] co_filename = '<?>'
    co_varnames = ()
    co_flags    = 67
      7           0 LOAD_CONST               1 (1)
                  3 PRINT_ITEM          
                  4 PRINT_NEWLINE       
                  5 LOAD_CONST               0 (None)
                  8 RETURN_VALUE        
    co_consts:
    [0] None
    [1] 1
[4] 1
[5] 'asd'
[6] 'A'
[7] co_filename = '<?>'
    co_varnames = ()
    co_flags    = 66
     12           0 LOAD_GLOBAL              0 (__name__)
                  3 STORE_NAME               1 (__module__)
    
     13           6 LOAD_CONST               1 (<pypy.interpreter.pycode.PyCode object at xxx>)
                  9 MAKE_FUNCTION            0
                 12 STORE_NAME               2 (f)
                 15 LOAD_LOCALS         
                 16 RETURN_VALUE        
    co_consts:
    [0] None
    [1] co_filename = '<?>'
        co_varnames = ()
        co_flags    = 67
         13           0 LOAD_CONST               0 (None)
                      3 RETURN_VALUE        
        co_consts:
        [0] None
