a = 1
a = -1
a = 1.
a = .2
a = 1.2
a = 1e3
a = 1.3e4
a = -1.3

===============================================================================
co_filename = '<?>'
co_varnames = ()
co_flags    = 64
  1           0 LOAD_CONST               1 (1)
              3 STORE_NAME               0 (a)

  2           6 LOAD_CONST               1 (1)
              9 UNARY_NEGATIVE      
             10 STORE_NAME               0 (a)

  3          13 LOAD_CONST               2 (1.0)
             16 STORE_NAME               0 (a)

  4          19 LOAD_CONST               3 (0.20000000000000001)
             22 STORE_NAME               0 (a)

  5          25 LOAD_CONST               4 (1.2)
             28 STORE_NAME               0 (a)

  6          31 LOAD_CONST               5 (1000.0)
             34 STORE_NAME               0 (a)

  7          37 LOAD_CONST               6 (13000.0)
             40 STORE_NAME               0 (a)

  8          43 LOAD_CONST               7 (1.3)
             46 UNARY_NEGATIVE      
             47 STORE_NAME               0 (a)
             50 LOAD_CONST               0 (None)
             53 RETURN_VALUE        
co_consts:
[0] None
[1] 1
[2] 1.0
[3] 0.20000000000000001
[4] 1.2
[5] 1000.0
[6] 13000.0
[7] 1.3
