[i for i in range(10) if i%2 == 0]
# same list on several lines
[i for i in range(10)
 if i%2 == 0]
[i for i in 1,2]
[(i,j) for i in 1,2 for j in 3,4]

===============================================================================
co_filename = '<?>'
co_varnames = ()
co_flags    = 64
  1           0 BUILD_LIST               0
              3 DUP_TOP             
              4 LOAD_ATTR                0 (append)
              7 STORE_NAME               1 ($append0)
             10 LOAD_NAME                2 (range)
             13 LOAD_CONST               1 (10)
             16 CALL_FUNCTION            1
             19 GET_ITER            
        >>   20 FOR_ITER                37 (to 60)
             23 STORE_NAME               3 (i)
             26 LOAD_NAME                3 (i)
             29 LOAD_CONST               2 (2)
             32 BINARY_MODULO       
             33 LOAD_CONST               3 (0)
             36 COMPARE_OP               2 (==)
             39 JUMP_IF_FALSE           14 (to 56)
             42 POP_TOP             
             43 LOAD_NAME                1 ($append0)
             46 LOAD_NAME                3 (i)
             49 CALL_FUNCTION            1
             52 POP_TOP             
             53 JUMP_FORWARD             1 (to 57)
        >>   56 POP_TOP             
        >>   57 JUMP_ABSOLUTE           20
        >>   60 DELETE_NAME              1 ($append0)
             63 POP_TOP             

  3          64 BUILD_LIST               0
             67 DUP_TOP             
             68 LOAD_ATTR                0 (append)
             71 STORE_NAME               1 ($append0)
             74 LOAD_NAME                2 (range)
             77 LOAD_CONST               1 (10)
             80 CALL_FUNCTION            1
             83 GET_ITER            
        >>   84 FOR_ITER                37 (to 124)
             87 STORE_NAME               3 (i)

  4          90 LOAD_NAME                3 (i)
             93 LOAD_CONST               2 (2)
             96 BINARY_MODULO       
             97 LOAD_CONST               3 (0)
            100 COMPARE_OP               2 (==)
            103 JUMP_IF_FALSE           14 (to 120)
            106 POP_TOP             
            107 LOAD_NAME                1 ($append0)
            110 LOAD_NAME                3 (i)
            113 CALL_FUNCTION            1
            116 POP_TOP             
            117 JUMP_FORWARD             1 (to 121)
        >>  120 POP_TOP             
        >>  121 JUMP_ABSOLUTE           84
        >>  124 DELETE_NAME              1 ($append0)
            127 POP_TOP             

  5         128 BUILD_LIST               0
            131 DUP_TOP             
            132 LOAD_ATTR                0 (append)
            135 STORE_NAME               1 ($append0)
            138 LOAD_CONST               4 (1)
            141 LOAD_CONST               2 (2)
            144 BUILD_TUPLE              2
            147 GET_ITER            
        >>  148 FOR_ITER                16 (to 167)
            151 STORE_NAME               3 (i)
            154 LOAD_NAME                1 ($append0)
            157 LOAD_NAME                3 (i)
            160 CALL_FUNCTION            1
            163 POP_TOP             
            164 JUMP_ABSOLUTE          148
        >>  167 DELETE_NAME              1 ($append0)
            170 POP_TOP             

  6         171 BUILD_LIST               0
            174 DUP_TOP             
            175 LOAD_ATTR                0 (append)
            178 STORE_NAME               1 ($append0)
            181 LOAD_CONST               4 (1)
            184 LOAD_CONST               2 (2)
            187 BUILD_TUPLE              2
            190 GET_ITER            
        >>  191 FOR_ITER                41 (to 235)
            194 STORE_NAME               3 (i)
            197 LOAD_CONST               5 (3)
            200 LOAD_CONST               6 (4)
            203 BUILD_TUPLE              2
            206 GET_ITER            
        >>  207 FOR_ITER                22 (to 232)
            210 STORE_NAME               4 (j)
            213 LOAD_NAME                1 ($append0)
            216 LOAD_NAME                3 (i)
            219 LOAD_NAME                4 (j)
            222 BUILD_TUPLE              2
            225 CALL_FUNCTION            1
            228 POP_TOP             
            229 JUMP_ABSOLUTE          207
        >>  232 JUMP_ABSOLUTE          191
        >>  235 DELETE_NAME              1 ($append0)
            238 POP_TOP             
            239 LOAD_CONST               0 (None)
            242 RETURN_VALUE        
co_consts:
[0] None
[1] 10
[2] 2
[3] 0
[4] 1
[5] 3
[6] 4
