try:
    a
    b
except:
    pass

try:
    a
    b
except NameError:
    pass

try:
    a
    b
except NameError, err:
    pass

try:
    a
    b
except (NameError, ValueError):
    pass


try:
    a
    b
except (NameError, ValueError), err:
    pass

try:
    a
except NameError, err:
    pass
except ValueError, err:
    pass

try:
    a
except NameError, err:
    pass
except ValueError, err:
    pass
else:
    pass

try:
    a
finally:
    b




===============================================================================
co_filename = '<?>'
co_varnames = ()
co_flags    = 64
  1           0 SETUP_EXCEPT            12 (to 15)

  2           3 LOAD_NAME                0 (a)
              6 POP_TOP             

  3           7 LOAD_NAME                1 (b)
             10 POP_TOP             
             11 POP_BLOCK           
             12 JUMP_FORWARD             7 (to 22)
        >>   15 POP_TOP             
             16 POP_TOP             
             17 POP_TOP             

  5          18 JUMP_FORWARD             1 (to 22)
             21 END_FINALLY         

  7     >>   22 SETUP_EXCEPT            12 (to 37)

  8          25 LOAD_NAME                0 (a)
             28 POP_TOP             

  9          29 LOAD_NAME                1 (b)
             32 POP_TOP             
             33 POP_BLOCK           
             34 JUMP_FORWARD            19 (to 56)

 10     >>   37 DUP_TOP             
             38 LOAD_NAME                2 (NameError)
             41 COMPARE_OP              10 (exception match)
             44 JUMP_IF_FALSE            7 (to 54)
             47 POP_TOP             
             48 POP_TOP             
             49 POP_TOP             
             50 POP_TOP             

 11          51 JUMP_FORWARD             2 (to 56)
        >>   54 POP_TOP             
             55 END_FINALLY         

 13     >>   56 SETUP_EXCEPT            12 (to 71)

 14          59 LOAD_NAME                0 (a)
             62 POP_TOP             

 15          63 LOAD_NAME                1 (b)
             66 POP_TOP             
             67 POP_BLOCK           
             68 JUMP_FORWARD            21 (to 92)

 16     >>   71 DUP_TOP             
             72 LOAD_NAME                2 (NameError)
             75 COMPARE_OP              10 (exception match)
             78 JUMP_IF_FALSE            9 (to 90)
             81 POP_TOP             
             82 POP_TOP             
             83 STORE_NAME               3 (err)
             86 POP_TOP             

 17          87 JUMP_FORWARD             2 (to 92)
        >>   90 POP_TOP             
             91 END_FINALLY         

 19     >>   92 SETUP_EXCEPT            12 (to 107)

 20          95 LOAD_NAME                0 (a)
             98 POP_TOP             

 21          99 LOAD_NAME                1 (b)
            102 POP_TOP             
            103 POP_BLOCK           
            104 JUMP_FORWARD            25 (to 132)

 22     >>  107 DUP_TOP             
            108 LOAD_NAME                2 (NameError)
            111 LOAD_NAME                4 (ValueError)
            114 BUILD_TUPLE              2
            117 COMPARE_OP              10 (exception match)
            120 JUMP_IF_FALSE            7 (to 130)
            123 POP_TOP             
            124 POP_TOP             
            125 POP_TOP             
            126 POP_TOP             

 23         127 JUMP_FORWARD             2 (to 132)
        >>  130 POP_TOP             
            131 END_FINALLY         

 26     >>  132 SETUP_EXCEPT            12 (to 147)

 27         135 LOAD_NAME                0 (a)
            138 POP_TOP             

 28         139 LOAD_NAME                1 (b)
            142 POP_TOP             
            143 POP_BLOCK           
            144 JUMP_FORWARD            27 (to 174)

 29     >>  147 DUP_TOP             
            148 LOAD_NAME                2 (NameError)
            151 LOAD_NAME                4 (ValueError)
            154 BUILD_TUPLE              2
            157 COMPARE_OP              10 (exception match)
            160 JUMP_IF_FALSE            9 (to 172)
            163 POP_TOP             
            164 POP_TOP             
            165 STORE_NAME               3 (err)
            168 POP_TOP             

 30         169 JUMP_FORWARD             2 (to 174)
        >>  172 POP_TOP             
            173 END_FINALLY         

 32     >>  174 SETUP_EXCEPT             8 (to 185)

 33         177 LOAD_NAME                0 (a)
            180 POP_TOP             
            181 POP_BLOCK           
            182 JUMP_FORWARD            41 (to 226)

 34     >>  185 DUP_TOP             
            186 LOAD_NAME                2 (NameError)
            189 COMPARE_OP              10 (exception match)
            192 JUMP_IF_FALSE            9 (to 204)
            195 POP_TOP             
            196 POP_TOP             
            197 STORE_NAME               3 (err)
            200 POP_TOP             

 35         201 JUMP_FORWARD            22 (to 226)
        >>  204 POP_TOP             

 36         205 DUP_TOP             
            206 LOAD_NAME                4 (ValueError)
            209 COMPARE_OP              10 (exception match)
            212 JUMP_IF_FALSE            9 (to 224)
            215 POP_TOP             
            216 POP_TOP             
            217 STORE_NAME               3 (err)
            220 POP_TOP             

 37         221 JUMP_FORWARD             2 (to 226)
        >>  224 POP_TOP             
            225 END_FINALLY         

 39     >>  226 SETUP_EXCEPT             8 (to 237)

 40         229 LOAD_NAME                0 (a)
            232 POP_TOP             
            233 POP_BLOCK           
            234 JUMP_FORWARD            41 (to 278)

 41     >>  237 DUP_TOP             
            238 LOAD_NAME                2 (NameError)
            241 COMPARE_OP              10 (exception match)
            244 JUMP_IF_FALSE            9 (to 256)
            247 POP_TOP             
            248 POP_TOP             
            249 STORE_NAME               3 (err)
            252 POP_TOP             

 42         253 JUMP_FORWARD            22 (to 278)
        >>  256 POP_TOP             

 43         257 DUP_TOP             
            258 LOAD_NAME                4 (ValueError)
            261 COMPARE_OP              10 (exception match)
            264 JUMP_IF_FALSE            9 (to 276)
            267 POP_TOP             
            268 POP_TOP             
            269 STORE_NAME               3 (err)
            272 POP_TOP             

 44         273 JUMP_FORWARD             2 (to 278)
        >>  276 POP_TOP             
            277 END_FINALLY         

 48     >>  278 SETUP_FINALLY            8 (to 289)

 49         281 LOAD_NAME                0 (a)
            284 POP_TOP             
            285 POP_BLOCK           
            286 LOAD_CONST               0 (None)

 51     >>  289 LOAD_NAME                1 (b)
            292 POP_TOP             
            293 END_FINALLY         
            294 LOAD_CONST               0 (None)
            297 RETURN_VALUE        
co_consts:
[0] None
