a = 1
b = 2
c = a + b

===============================================================================
co_filename = '<?>'
co_varnames = ()
co_flags    = 64
  1           0 LOAD_CONST               1 (1)
              3 STORE_NAME               0 (a)

  2           6 LOAD_CONST               2 (2)
              9 STORE_NAME               1 (b)

  3          12 LOAD_NAME                0 (a)
             15 LOAD_NAME                1 (b)
             18 BINARY_ADD          
             19 STORE_NAME               2 (c)
             22 LOAD_CONST               0 (None)
             25 RETURN_VALUE        
co_consts:
[0] None
[1] 1
[2] 2
