while (a < b and c < d
       and e < f):
    pass

while (a < b and
       c < d
       and e < f):
    pass

while (a < b
       and c < d
       and e < f):
    pass

while (a < b
       and c < d and
       e < f):
    pass

===============================================================================
co_filename = '<?>'
co_varnames = ()
co_flags    = 64
  1           0 SETUP_LOOP              44 (to 47)
        >>    3 LOAD_NAME                0 (a)
              6 LOAD_NAME                1 (b)
              9 COMPARE_OP               0 (<)
             12 JUMP_IF_FALSE           23 (to 38)
             15 POP_TOP             
             16 LOAD_NAME                2 (c)
             19 LOAD_NAME                3 (d)
             22 COMPARE_OP               0 (<)
             25 JUMP_IF_FALSE           10 (to 38)
             28 POP_TOP             

  2          29 LOAD_NAME                4 (e)
             32 LOAD_NAME                5 (f)
             35 COMPARE_OP               0 (<)
        >>   38 JUMP_IF_FALSE            4 (to 45)
             41 POP_TOP             

  3          42 JUMP_ABSOLUTE            3
        >>   45 POP_TOP             
             46 POP_BLOCK           

  5     >>   47 SETUP_LOOP              44 (to 94)
        >>   50 LOAD_NAME                0 (a)
             53 LOAD_NAME                1 (b)
             56 COMPARE_OP               0 (<)
             59 JUMP_IF_FALSE           23 (to 85)
             62 POP_TOP             

  6          63 LOAD_NAME                2 (c)
             66 LOAD_NAME                3 (d)
             69 COMPARE_OP               0 (<)
             72 JUMP_IF_FALSE           10 (to 85)
             75 POP_TOP             

  7          76 LOAD_NAME                4 (e)
             79 LOAD_NAME                5 (f)
             82 COMPARE_OP               0 (<)
        >>   85 JUMP_IF_FALSE            4 (to 92)
             88 POP_TOP             

  8          89 JUMP_ABSOLUTE           50
        >>   92 POP_TOP             
             93 POP_BLOCK           

 10     >>   94 SETUP_LOOP              44 (to 141)
        >>   97 LOAD_NAME                0 (a)
            100 LOAD_NAME                1 (b)
            103 COMPARE_OP               0 (<)
            106 JUMP_IF_FALSE           23 (to 132)
            109 POP_TOP             

 11         110 LOAD_NAME                2 (c)
            113 LOAD_NAME                3 (d)
            116 COMPARE_OP               0 (<)
            119 JUMP_IF_FALSE           10 (to 132)
            122 POP_TOP             

 12         123 LOAD_NAME                4 (e)
            126 LOAD_NAME                5 (f)
            129 COMPARE_OP               0 (<)
        >>  132 JUMP_IF_FALSE            4 (to 139)
            135 POP_TOP             

 13         136 JUMP_ABSOLUTE           97
        >>  139 POP_TOP             
            140 POP_BLOCK           

 15     >>  141 SETUP_LOOP              44 (to 188)
        >>  144 LOAD_NAME                0 (a)
            147 LOAD_NAME                1 (b)
            150 COMPARE_OP               0 (<)
            153 JUMP_IF_FALSE           23 (to 179)
            156 POP_TOP             

 16         157 LOAD_NAME                2 (c)
            160 LOAD_NAME                3 (d)
            163 COMPARE_OP               0 (<)
            166 JUMP_IF_FALSE           10 (to 179)
            169 POP_TOP             

 17         170 LOAD_NAME                4 (e)
            173 LOAD_NAME                5 (f)
            176 COMPARE_OP               0 (<)
        >>  179 JUMP_IF_FALSE            4 (to 186)
            182 POP_TOP             

 18         183 JUMP_ABSOLUTE          144
        >>  186 POP_TOP             
            187 POP_BLOCK           
        >>  188 LOAD_CONST               0 (None)
            191 RETURN_VALUE        
co_consts:
[0] None
