class A:
    def with_white_spaces_before(self):
        pass

    def another_method(self, foo):
        bar = foo


class B(object, A):
    def foo(self, bar):
        a = 2
        return "spam"

===============================================================================
co_filename = '<?>'
co_varnames = ()
co_flags    = 64
  1           0 LOAD_CONST               1 ('A')
              3 BUILD_TUPLE              0
              6 LOAD_CONST               2 (<pypy.interpreter.pycode.PyCode object at xxx>)
              9 MAKE_FUNCTION            0
             12 CALL_FUNCTION            0
             15 BUILD_CLASS         
             16 STORE_NAME               0 (A)

  9          19 LOAD_CONST               3 ('B')
             22 LOAD_NAME                1 (object)
             25 LOAD_NAME                0 (A)
             28 BUILD_TUPLE              2
             31 LOAD_CONST               4 (<pypy.interpreter.pycode.PyCode object at xxx>)
             34 MAKE_FUNCTION            0
             37 CALL_FUNCTION            0
             40 BUILD_CLASS         
             41 STORE_NAME               2 (B)
             44 LOAD_CONST               0 (None)
             47 RETURN_VALUE        
co_consts:
[0] None
[1] 'A'
[2] co_filename = '<?>'
    co_varnames = ()
    co_flags    = 66
      1           0 LOAD_GLOBAL              0 (__name__)
                  3 STORE_NAME               1 (__module__)
    
      2           6 LOAD_CONST               1 (<pypy.interpreter.pycode.PyCode object at xxx>)
                  9 MAKE_FUNCTION            0
                 12 STORE_NAME               2 (with_white_spaces_before)
    
      5          15 LOAD_CONST               2 (<pypy.interpreter.pycode.PyCode object at xxx>)
                 18 MAKE_FUNCTION            0
                 21 STORE_NAME               3 (another_method)
                 24 LOAD_LOCALS         
                 25 RETURN_VALUE        
    co_consts:
    [0] None
    [1] co_filename = '<?>'
        co_varnames = ('self',)
        co_flags    = 67
          2           0 LOAD_CONST               0 (None)
                      3 RETURN_VALUE        
        co_consts:
        [0] None
    [2] co_filename = '<?>'
        co_varnames = ('self', 'foo', 'bar')
        co_flags    = 67
          6           0 LOAD_FAST                1 (foo)
                      3 STORE_FAST               2 (bar)
                      6 LOAD_CONST               0 (None)
                      9 RETURN_VALUE        
        co_consts:
        [0] None
[3] 'B'
[4] co_filename = '<?>'
    co_varnames = ()
    co_flags    = 66
      9           0 LOAD_GLOBAL              0 (__name__)
                  3 STORE_NAME               1 (__module__)
    
     10           6 LOAD_CONST               1 (<pypy.interpreter.pycode.PyCode object at xxx>)
                  9 MAKE_FUNCTION            0
                 12 STORE_NAME               2 (foo)
                 15 LOAD_LOCALS         
                 16 RETURN_VALUE        
    co_consts:
    [0] None
    [1] co_filename = '<?>'
        co_varnames = ('self', 'bar', 'a')
        co_flags    = 67
         11           0 LOAD_CONST               1 (2)
                      3 STORE_FAST               2 (a)
        
         12           6 LOAD_CONST               2 ('spam')
                      9 RETURN_VALUE        
                     10 LOAD_CONST               0 (None)
                     13 RETURN_VALUE        
        co_consts:
        [0] None
        [1] 2
        [2] 'spam'
