f()
f(a)
f(a,)
f(a,b)
f(a, b,)
f(*args)
f(**kwargs)
f(*args, **kwargs)
f(a, *args, **kwargs)
f(a, b, *args, **kwargs)
a = 1

===============================================================================
co_filename = '<?>'
co_varnames = ()
co_flags    = 64
  1           0 LOAD_NAME                0 (f)
              3 CALL_FUNCTION            0
              6 POP_TOP             

  2           7 LOAD_NAME                0 (f)
             10 LOAD_NAME                1 (a)
             13 CALL_FUNCTION            1
             16 POP_TOP             

  3          17 LOAD_NAME                0 (f)
             20 LOAD_NAME                1 (a)
             23 CALL_FUNCTION            1
             26 POP_TOP             

  4          27 LOAD_NAME                0 (f)
             30 LOAD_NAME                1 (a)
             33 LOAD_NAME                2 (b)
             36 CALL_FUNCTION            2
             39 POP_TOP             

  5          40 LOAD_NAME                0 (f)
             43 LOAD_NAME                1 (a)
             46 LOAD_NAME                2 (b)
             49 CALL_FUNCTION            2
             52 POP_TOP             

  6          53 LOAD_NAME                0 (f)
             56 LOAD_NAME                3 (args)
             59 CALL_FUNCTION_VAR        0
             62 POP_TOP             

  7          63 LOAD_NAME                0 (f)
             66 LOAD_NAME                4 (kwargs)
             69 CALL_FUNCTION_KW         0
             72 POP_TOP             

  8          73 LOAD_NAME                0 (f)
             76 LOAD_NAME                3 (args)
             79 LOAD_NAME                4 (kwargs)
             82 CALL_FUNCTION_VAR_KW     0
             85 POP_TOP             

  9          86 LOAD_NAME                0 (f)
             89 LOAD_NAME                1 (a)
             92 LOAD_NAME                3 (args)
             95 LOAD_NAME                4 (kwargs)
             98 CALL_FUNCTION_VAR_KW     1
            101 POP_TOP             

 10         102 LOAD_NAME                0 (f)
            105 LOAD_NAME                1 (a)
            108 LOAD_NAME                2 (b)
            111 LOAD_NAME                3 (args)
            114 LOAD_NAME                4 (kwargs)
            117 CALL_FUNCTION_VAR_KW     2
            120 POP_TOP             

 11         121 LOAD_CONST               1 (1)
            124 STORE_NAME               1 (a)
            127 LOAD_CONST               0 (None)
            130 RETURN_VALUE        
co_consts:
[0] None
[1] 1
