"""module docstring"""


"""hello

"""

class A:
    """class doctring

    on several lines
    """

def foo(self):
    """function docstring"""

def boo(x):
    """Docstring""";print 1

"""world"""

===============================================================================
co_filename = '<?>'
co_varnames = ()
co_flags    = 64
  1           0 LOAD_CONST               1 ('module docstring')
              3 STORE_NAME               0 (__doc__)

  8           6 LOAD_CONST               2 ('A')
              9 BUILD_TUPLE              0
             12 LOAD_CONST               3 (<pypy.interpreter.pycode.PyCode object at xxx>)
             15 MAKE_FUNCTION            0
             18 CALL_FUNCTION            0
             21 BUILD_CLASS         
             22 STORE_NAME               1 (A)

 14          25 LOAD_CONST               4 (<pypy.interpreter.pycode.PyCode object at xxx>)
             28 MAKE_FUNCTION            0
             31 STORE_NAME               2 (foo)

 17          34 LOAD_CONST               5 (<pypy.interpreter.pycode.PyCode object at xxx>)
             37 MAKE_FUNCTION            0
             40 STORE_NAME               3 (boo)
             43 LOAD_CONST               6 (None)
             46 RETURN_VALUE        
co_consts:
[0] 'Docstring'
[1] 'module docstring'
[2] 'A'
[3] co_filename = '<?>'
    co_varnames = ()
    co_flags    = 66
      8           0 LOAD_GLOBAL              0 (__name__)
                  3 STORE_NAME               1 (__module__)
                  6 LOAD_CONST               0 ('class doctring\n\n    on several lines\n    ')
                  9 STORE_NAME               2 (__doc__)
                 12 LOAD_LOCALS         
                 13 RETURN_VALUE        
    co_consts:
    [0] 'class doctring\n\n    on several lines\n    '
[4] co_filename = '<?>'
    co_varnames = ('self',)
    co_flags    = 67
     14           0 LOAD_CONST               1 (None)
                  3 RETURN_VALUE        
    co_consts:
    [0] 'function docstring'
    [1] None
[5] co_filename = '<?>'
    co_varnames = ('x',)
    co_flags    = 67
     18           0 LOAD_CONST               1 (1)
                  3 PRINT_ITEM          
                  4 PRINT_NEWLINE       
                  5 LOAD_CONST               2 (None)
                  8 RETURN_VALUE        
    co_consts:
    [0] 'Docstring'
    [1] 1
    [2] None
[6] None
