x = 0x1L # comment
a = 1 # yo
 # hello
# world
a = 2
# end

===============================================================================
co_filename = '<?>'
co_varnames = ()
co_flags    = 64
  1           0 LOAD_CONST               1 (1L)
              3 STORE_NAME               0 (x)

  2           6 LOAD_CONST               2 (1)
              9 STORE_NAME               1 (a)

  5          12 LOAD_CONST               3 (2)
             15 STORE_NAME               1 (a)
             18 LOAD_CONST               0 (None)
             21 RETURN_VALUE        
co_consts:
[0] None
[1] 1L
[2] 1
[3] 2
