l = [ "foo", "bar",
      "baz"]

l = [
    "foo",
    "bar",
    "baz",
    ]

l = []
l = [
    ]

===============================================================================
co_filename = '<?>'
co_varnames = ()
co_flags    = 64
  1           0 LOAD_CONST               1 ('foo')
              3 LOAD_CONST               2 ('bar')
              6 LOAD_CONST               3 ('baz')
              9 BUILD_LIST               3
             12 STORE_NAME               0 (l)

  4          15 LOAD_CONST               1 ('foo')
             18 LOAD_CONST               2 ('bar')
             21 LOAD_CONST               3 ('baz')
             24 BUILD_LIST               3
             27 STORE_NAME               0 (l)

 10          30 BUILD_LIST               0
             33 STORE_NAME               0 (l)

 11          36 BUILD_LIST               0
             39 STORE_NAME               0 (l)
             42 LOAD_CONST               0 (None)
             45 RETURN_VALUE        
co_consts:
[0] None
[1] 'foo'
[2] 'bar'
[3] 'baz'
