def f(a, b=1, *args, **kwargs):
    if args:
        a += len(args)
    if kwargs:
        a += len(kwargs)
    return a*b

===============================================================================
co_filename = '<?>'
co_varnames = ()
co_flags    = 64
  1           0 LOAD_CONST               1 (1)
              3 LOAD_CONST               2 (<pypy.interpreter.pycode.PyCode object at xxx>)
              6 MAKE_FUNCTION            1
              9 STORE_NAME               0 (f)
             12 LOAD_CONST               0 (None)
             15 RETURN_VALUE        
co_consts:
[0] None
[1] 1
[2] co_filename = '<?>'
    co_varnames = ('a', 'b', 'args', 'kwargs')
    co_flags    = 79
      2           0 LOAD_FAST                2 (args)
                  3 JUMP_IF_FALSE           20 (to 26)
                  6 POP_TOP             
    
      3           7 LOAD_FAST                0 (a)
                 10 LOAD_GLOBAL              2 (len)
                 13 LOAD_FAST                2 (args)
                 16 CALL_FUNCTION            1
                 19 INPLACE_ADD         
                 20 STORE_FAST               0 (a)
                 23 JUMP_FORWARD             1 (to 27)
            >>   26 POP_TOP             
    
      4     >>   27 LOAD_FAST                3 (kwargs)
                 30 JUMP_IF_FALSE           20 (to 53)
                 33 POP_TOP             
    
      5          34 LOAD_FAST                0 (a)
                 37 LOAD_GLOBAL              2 (len)
                 40 LOAD_FAST                3 (kwargs)
                 43 CALL_FUNCTION            1
                 46 INPLACE_ADD         
                 47 STORE_FAST               0 (a)
                 50 JUMP_FORWARD             1 (to 54)
            >>   53 POP_TOP             
    
      6     >>   54 LOAD_FAST                0 (a)
                 57 LOAD_FAST                1 (b)
                 60 BINARY_MULTIPLY     
                 61 RETURN_VALUE        
                 62 LOAD_CONST               0 (None)
                 65 RETURN_VALUE        
    co_consts:
    [0] None
