def f(n):
    for i in range(n):
        yield n

===============================================================================
co_filename = '<?>'
co_varnames = ()
co_flags    = 64
  1           0 LOAD_CONST               1 (<pypy.interpreter.pycode.PyCode object at xxx>)
              3 MAKE_FUNCTION            0
              6 STORE_NAME               0 (f)
              9 LOAD_CONST               0 (None)
             12 RETURN_VALUE        
co_consts:
[0] None
[1] co_filename = '<?>'
    co_varnames = ('n', 'i')
    co_flags    = 99
      2           0 SETUP_LOOP              24 (to 27)
                  3 LOAD_GLOBAL              0 (range)
                  6 LOAD_FAST                0 (n)
                  9 CALL_FUNCTION            1
                 12 GET_ITER            
            >>   13 FOR_ITER                10 (to 26)
                 16 STORE_FAST               1 (i)
    
      3          19 LOAD_FAST                0 (n)
                 22 YIELD_VALUE         
                 23 JUMP_ABSOLUTE           13
            >>   26 POP_BLOCK           
            >>   27 LOAD_CONST               0 (None)
                 30 RETURN_VALUE        
    co_consts:
    [0] None
